COPYING
README
setup.cfg
setup.py
kid/proxypage.kid
rdfa2rdf/__init__.py
rdfa2rdf/h2aproxy.py
rdfa2rdf/r2rproxy.py
rdfa2rdf/settings.py
rdfa2rdf/util.py
rdfa2rdf.egg-info/PKG-INFO
rdfa2rdf.egg-info/SOURCES.txt
rdfa2rdf.egg-info/dependency_links.txt
rdfa2rdf.egg-info/entry_points.txt
rdfa2rdf.egg-info/requires.txt
rdfa2rdf.egg-info/top_level.txt
