Metadata-Version: 1.0
Name: rdfa2rdf
Version: 0.1
Summary: WSGI proxy for transforming RDFa to RDF via RDFa2RDFXML.xsl.
Home-page: http://tools.weborganics.co.uk
Author: Luke Arno, this version Martin McEvoy
Author-email: luke.arno@gmail.com, martin@weborganics.co.uk
License: GPL2
Keywords: RDRa RDF wsgi proxy
Platform: UNKNOWN
Classifier: Development Status :: 1 - Alpha
Classifier: Environment :: Web Environment
Classifier: Intended Audience :: Developers
Classifier: License :: OSI Approved :: GNU General Public License (GPL)
Classifier: Natural Language :: English
Classifier: Operating System :: OS Independent
Classifier: Programming Language :: Python
Classifier: Topic :: Internet :: WWW/HTTP
Classifier: Topic :: Text Processing :: Markup :: XML
Classifier: Topic :: Text Processing :: Markup :: HTML
